example_pkg_matkoniecz/__init__.py
example_pkg_matkoniecz/lorem_ipsum.py
example_pkg_matkoniecz-0.1.3.dist-info/LICENSE
example_pkg_matkoniecz-0.1.3.dist-info/METADATA
example_pkg_matkoniecz-0.1.3.dist-info/WHEEL
example_pkg_matkoniecz-0.1.3.dist-info/top_level.txt
example_pkg_matkoniecz-0.1.3.dist-info/RECORD
