Metadata-Version: 2.1
Name: example-pkg-matkoniecz
Version: 0.1.3
Summary: A small example package
Home-page: https://github.com/matkoniecz/example_python_package
Author: Example Author
Author-email: author@example.com
License: UNKNOWN
Platform: UNKNOWN
Classifier: Programming Language :: Python :: 3
Classifier: License :: OSI Approved :: MIT License
Classifier: Operating System :: OS Independent
